MANIFEST.in
README.md
setup.py
streamlit_sweethome3d/__init__.py
streamlit_sweethome3d/pypi_readme.md
streamlit_sweethome3d.egg-info/PKG-INFO
streamlit_sweethome3d.egg-info/SOURCES.txt
streamlit_sweethome3d.egg-info/dependency_links.txt
streamlit_sweethome3d.egg-info/requires.txt
streamlit_sweethome3d.egg-info/top_level.txt
streamlit_sweethome3d/frontend/dist/index.html
streamlit_sweethome3d/frontend/dist/vite.svg
streamlit_sweethome3d/frontend/dist/assets/index-itB7MvgZ.js
streamlit_sweethome3d/frontend/dist/lib/batik-svgpathparser.min.js
streamlit_sweethome3d/frontend/dist/lib/big.min.js
streamlit_sweethome3d/frontend/dist/lib/close.png
streamlit_sweethome3d/frontend/dist/lib/core.min.js
streamlit_sweethome3d/frontend/dist/lib/geom.min.js
streamlit_sweethome3d/frontend/dist/lib/gl-matrix-min.js
streamlit_sweethome3d/frontend/dist/lib/graphics2d.min.js
streamlit_sweethome3d/frontend/dist/lib/jsXmlSaxParser.min.js
streamlit_sweethome3d/frontend/dist/lib/jszip.min.js
streamlit_sweethome3d/frontend/dist/lib/menu.png
streamlit_sweethome3d/frontend/dist/lib/navigationPanel.png
streamlit_sweethome3d/frontend/dist/lib/recorderworker.min.js
streamlit_sweethome3d/frontend/dist/lib/search.gif
streamlit_sweethome3d/frontend/dist/lib/stroke.min.js
streamlit_sweethome3d/frontend/dist/lib/sweethome3d.min.js
streamlit_sweethome3d/frontend/dist/lib/sweethome3djs.css
streamlit_sweethome3d/frontend/dist/lib/swingundo.min.js
streamlit_sweethome3d/frontend/dist/lib/triangulator.min.js
streamlit_sweethome3d/frontend/dist/lib/resources/DefaultFurnitureCatalog.json
streamlit_sweethome3d/frontend/dist/lib/resources/DefaultFurnitureCatalog_bg.json
streamlit_sweethome3d/frontend/dist/lib/resources/DefaultFurnitureCatalog_cs.json
streamlit_sweethome3d/frontend/dist/lib/resources/DefaultFurnitureCatalog_de.json
streamlit_sweethome3d/frontend/dist/lib/resources/DefaultFurnitureCatalog_el.json
streamlit_sweethome3d/frontend/dist/lib/resources/DefaultFurnitureCatalog_en_US.json
streamlit_sweethome3d/frontend/dist/lib/resources/DefaultFurnitureCatalog_es.json
streamlit_sweethome3d/frontend/dist/lib/resources/DefaultFurnitureCatalog_fr.json
