Metadata-Version: 2.1
Name: streamlit-sweethome3d
Version: 0.0.6
Summary: This library is created for streamlit framework, it allow to creating house and insert furniture based on sweethome3djs with a good 3D view.
Home-page: https://gitlab.com/nicolalandro/streamlit-sweethome3d
Author: Nicola Landro
Author-email: nicolaxx94@live.it
Project-URL: Source, https://gitlab.com/nicolalandro/streamlit-sweethome3d
Keywords: 3d,house planner,streamlit
Requires-Python: >=3.6
